nxml/__init__.py
nxml/core.py
nxml/jax/__init__.py
nxml/jax/experimental/__init__.py
nxml/jax/experimental/utils.py
nxml/jax/nn/__init__.py
nxml/jax/nn/functional.py
nxml/numpy/__init__.py
nxml/numpy/nn/__init__.py
nxml/numpy/nn/functional.py
nxml/tensorflow/__init__.py
nxml/tensorflow/nn/__init__.py
nxml/tensorflow/nn/functional.py
nxml/torch/__init__.py
nxml/torch/engine/__init__.py
nxml/torch/engine/comm.py
nxml/torch/engine/launch.py
nxml/torch/engine/utils.py
nxml/torch/engine/xla/__init__.py
nxml/torch/engine/xla/launch.py
nxml/torch/nn/__init__.py
nxml/torch/nn/functional.py
nxml/univ/__init__.py
nxml/univ/nn/__init__.py
nxml/univ/nn/functional.py
nxml-0.0.3.dist-info/LICENSE
nxml-0.0.3.dist-info/METADATA
nxml-0.0.3.dist-info/WHEEL
nxml-0.0.3.dist-info/top_level.txt
nxml-0.0.3.dist-info/zip-safe
nxml-0.0.3.dist-info/RECORD
