Metadata-Version: 2.1
Name: nxml
Version: 0.0.3
Summary: NXML is an eXtension for Machine Learning
Home-page: https://github.com/yuneg11/nxml
Author: EungGu Yun
Author-email: yuneg11@gmail.com
License: MIT license
Project-URL: Documentation, https://yuneg11.github.io/NXML
Project-URL: Source, https://github.com/yuneg11/nxml
Project-URL: Tracker, https://github.com/yuneg11/nxml/issues
Keywords: nxml,NXML
Classifier: Operating System :: OS Independent
Classifier: License :: OSI Approved :: MIT License
Classifier: Programming Language :: Python :: 3
Classifier: Programming Language :: Python :: 3.7
Classifier: Programming Language :: Python :: 3.8
Classifier: Programming Language :: Python :: 3.9
Classifier: Programming Language :: Python :: 3.10
Classifier: Topic :: Scientific/Engineering :: Artificial Intelligence
Classifier: Topic :: Software Development :: Libraries :: Python Modules
Requires-Python: >=3.7
License-File: LICENSE
Requires-Dist: eagerpy (>=0.30)
